{
	"editor": {
		"allAngles": false,
		"entityTextureMode": false
	},
	"textureWidth": 16,
	"textureHeight": 16,
	"textureSizes": {
		"material": [32,32]
	},
	"textures": {
		"material": "game:item/tool/material/string"
	},
	"elements": [
		{
			"name": "origin",
			"from": [ 11.1, 0.5, 7.36 ],
			"to": [ 11.1, 0.5, 7.36 ],
			"rotationOrigin": [ 8.0972, 0.0, 7.6107 ],
			"faces": {
				"north": { "texture": "#0", "uv": [ 0.0, 0.0, 4.0, 4.0 ], "autoUv": false },
				"east": { "texture": "#0", "uv": [ 0.0, 0.0, 4.0, 4.0 ], "autoUv": false },
				"south": { "texture": "#0", "uv": [ 0.0, 0.0, 4.0, 4.0 ], "autoUv": false },
				"west": { "texture": "#0", "uv": [ 0.0, 0.0, 4.0, 4.0 ], "autoUv": false },
				"up": { "texture": "#material", "uv": [ 0.0, 0.0, 1.0, 1.0 ], "rotation": 180, "autoUv": false },
				"down": { "texture": "#0", "uv": [ 0.0, 0.0, 4.0, 4.0 ], "autoUv": false }
			},
			"children": [
				{
					"name": "binding_low_metalhead_unv 01",
					"from": [ -3.1242, -0.4644, -0.6006 ],
					"to": [ -2.5871, 0.9644, 1.2809 ],
					"rotationOrigin": [ -2.8557, 0.25, 0.3401 ],
					"rotationY": 21.3,
					"faces": {
						"north": { "texture": "#material", "uv": [ 18.4962, 1.9056, 21.4962, 2.9056 ], "rotation": 90, "autoUv": false },
						"east": { "texture": "#material", "uv": [ 1.4962, 0.9056, 5.6258, 3.9056 ], "autoUv": false },
						"south": { "texture": "#material", "uv": [ 3.4962, 1.9056, 6.4962, 2.9056 ], "rotation": 90, "autoUv": false },
						"west": { "texture": "#material", "uv": [ 5.3665, 5.9056, 9.4962, 8.9056 ], "autoUv": false },
						"up": { "texture": "#material", "uv": [ 1.4962, 0.7759, 2.4962, 4.9056 ], "autoUv": false },
						"down": { "texture": "#material", "uv": [ 2.4962, 4.9056, 1.4962, 0.7759 ], "rotation": 180, "autoUv": false }
					}
				},
				{
					"name": "binding_low_metalhead_unv 02",
					"from": [ -2.4853, -0.4954, -0.5651 ],
					"to": [ -1.9853, 0.9954, 1.1369 ],
					"rotationOrigin": [ -2.2353, 0.25, 0.2859 ],
					"rotationY": -0.43,
					"faces": {
						"north": { "texture": "#material", "uv": [ 18.4962, 1.9056, 21.4962, 2.9056 ], "rotation": 90, "autoUv": false },
						"east": { "texture": "#material", "uv": [ 1.6104, 0.9056, 5.6238, 3.9056 ], "autoUv": false },
						"south": { "texture": "#material", "uv": [ 3.4962, 1.9056, 6.4962, 2.9056 ], "rotation": 90, "autoUv": false },
						"west": { "texture": "#material", "uv": [ 5.3686, 5.9056, 9.3819, 8.9056 ], "autoUv": false },
						"up": { "texture": "#material", "uv": [ 1.4962, 0.778, 2.4962, 4.7913 ], "autoUv": false },
						"down": { "texture": "#material", "uv": [ 2.4962, 4.7913, 1.4962, 0.778 ], "rotation": 180, "autoUv": false }
					}
				},
				{
					"name": "binding_low_metalhead_unv 03",
					"from": [ 2.6904, 0.0042, -0.2749 ],
					"to": [ 5.454, 0.5042, 1.4895 ],
					"rotationOrigin": [ 4.0722, 0.2542, 0.6073 ],
					"rotationX": 90.9182,
					"rotationY": 0.3534,
					"rotationZ": -75.7526,
					"faces": {
						"north": { "texture": "#material", "uv": [ 10.3228, 0.9056, 15.8429, 1.9056 ], "autoUv": false },
						"east": { "texture": "#material", "uv": [ 3.2126, 1.9056, 6.7999, 2.9056 ], "rotation": 180, "autoUv": false },
						"south": { "texture": "#material", "uv": [ 6.3133, 4.9056, 11.8267, 5.9056 ], "rotation": 180, "autoUv": false },
						"west": { "texture": "#material", "uv": [ 1.2093, 5.9056, 4.7966, 6.9056 ], "autoUv": false },
						"up": { "texture": "#material", "uv": [ 0.1505, 4.6211, 5.678, 8.2084 ], "autoUv": false },
						"down": { "texture": "#material", "uv": [ 10.8418, 9.2084, 5.3143, 5.6211 ], "rotation": 180, "autoUv": false }
					}
				},
				{
					"name": "binding_low_metalhead_unv 04",
					"from": [ 3.2373, -0.02, -0.3292 ],
					"to": [ 5.8318, 0.48, 1.4464 ],
					"rotationOrigin": [ 4.5345, 0.23, 0.5586 ],
					"rotationX": 91.9901,
					"rotationY": -0.1093,
					"rotationZ": -68.562,
					"faces": {
						"north": { "texture": "#material", "uv": [ 7.4963, 1.9055, 12.6857, 2.9055 ], "autoUv": false },
						"east": { "texture": "#material", "uv": [ 1.4177, 1.9056, 4.6547, 2.9056 ], "rotation": 180, "autoUv": false },
						"south": { "texture": "#material", "uv": [ 14.4958, 1.9054, 19.6852, 2.9054 ], "rotation": 180, "autoUv": false },
						"west": { "texture": "#material", "uv": [ 5.4177, 1.9056, 8.6547, 2.9056 ], "autoUv": false },
						"up": { "texture": "#material", "uv": [ 0.3068, 0.8271, 5.4962, 4.0641 ], "autoUv": false },
						"down": { "texture": "#material", "uv": [ 6.6855, 12.0641, 1.4962, 8.8271 ], "rotation": 180, "autoUv": false }
					}
				},
				{
					"name": "binding_low_metalhead_unv 05",
					"from": [ 4.5304, -0.5153, -0.705 ],
					"to": [ 5.0304, 1.0749, 1.796 ],
					"rotationOrigin": [ 4.7804, 0.2798, 0.5455 ],
					"rotationY": 7.54,
					"faces": {
						"north": { "texture": "#material", "uv": [ 18.3793, 1.9056, 21.4962, 2.9056 ], "rotation": 90, "autoUv": false },
						"east": { "texture": "#material", "uv": [ 0.4942, 0.7887, 5.4962, 3.9056 ], "autoUv": false },
						"south": { "texture": "#material", "uv": [ 3.3793, 1.9056, 6.4962, 2.9056 ], "rotation": 90, "autoUv": false },
						"west": { "texture": "#material", "uv": [ 5.4962, 5.7887, 10.4981, 8.9056 ], "autoUv": false },
						"up": { "texture": "#material", "uv": [ 1.4962, 0.9056, 2.4962, 5.9075 ], "autoUv": false },
						"down": { "texture": "#material", "uv": [ 2.4962, 5.9075, 1.4962, 0.9056 ], "rotation": 180, "autoUv": false }
					}
				},
				{
					"name": "binding_low_metalhead_unv 06",
					"from": [ 4.7727, -0.658, 1.3272 ],
					"to": [ 5.0958, -0.3588, 2.2635 ],
					"rotationOrigin": [ 4.9342, -0.5084, 1.7954 ],
					"rotationX": 59.3265,
					"rotationY": -0.1095,
					"rotationZ": -68.4636,
					"faces": {
						"north": { "texture": "#material", "uv": [ 11.821, 2.107, 12.4673, 2.7054 ], "autoUv": false },
						"east": { "texture": "#material", "uv": [ 2.0905, 2.1062, 3.7975, 2.7046 ], "rotation": 180, "autoUv": false },
						"south": { "texture": "#material", "uv": [ 18.8239, 2.1071, 19.4702, 2.7055 ], "rotation": 180, "autoUv": false },
						"west": { "texture": "#material", "uv": [ 6.099, 2.1064, 7.8059, 2.7048 ], "autoUv": false },
						"up": { "texture": "#material", "uv": [ 0.5237, 1.5082, 1.17, 3.2151 ], "autoUv": false },
						"down": { "texture": "#material", "uv": [ 6.4686, 11.2148, 5.8223, 9.5078 ], "rotation": 180, "autoUv": false }
					}
				}
			]
		}
	]}